ophyd_async/__init__.py
ophyd_async/__main__.py
ophyd_async/_docs_parser.py
ophyd_async/_version.py
ophyd_async/py.typed
ophyd_async/core/__init__.py
ophyd_async/core/_derived_signal.py
ophyd_async/core/_derived_signal_backend.py
ophyd_async/core/_detector.py
ophyd_async/core/_device.py
ophyd_async/core/_device_filler.py
ophyd_async/core/_enums.py
ophyd_async/core/_flyer.py
ophyd_async/core/_hdf_dataset.py
ophyd_async/core/_log.py
ophyd_async/core/_mock_signal_backend.py
ophyd_async/core/_mock_signal_utils.py
ophyd_async/core/_protocol.py
ophyd_async/core/_providers.py
ophyd_async/core/_readable.py
ophyd_async/core/_settings.py
ophyd_async/core/_signal.py
ophyd_async/core/_signal_backend.py
ophyd_async/core/_soft_signal_backend.py
ophyd_async/core/_status.py
ophyd_async/core/_table.py
ophyd_async/core/_utils.py
ophyd_async/core/_yaml_settings.py
ophyd_async/epics/__init__.py
ophyd_async/epics/motor.py
ophyd_async/epics/signal.py
ophyd_async/epics/adandor/__init__.py
ophyd_async/epics/adandor/_andor.py
ophyd_async/epics/adandor/_andor_controller.py
ophyd_async/epics/adandor/_andor_io.py
ophyd_async/epics/adaravis/__init__.py
ophyd_async/epics/adaravis/_aravis.py
ophyd_async/epics/adaravis/_aravis_controller.py
ophyd_async/epics/adaravis/_aravis_io.py
ophyd_async/epics/adcore/__init__.py
ophyd_async/epics/adcore/_core_detector.py
ophyd_async/epics/adcore/_core_io.py
ophyd_async/epics/adcore/_core_logic.py
ophyd_async/epics/adcore/_core_writer.py
ophyd_async/epics/adcore/_hdf_writer.py
ophyd_async/epics/adcore/_jpeg_writer.py
ophyd_async/epics/adcore/_single_trigger.py
ophyd_async/epics/adcore/_tiff_writer.py
ophyd_async/epics/adcore/_utils.py
ophyd_async/epics/adkinetix/__init__.py
ophyd_async/epics/adkinetix/_kinetix.py
ophyd_async/epics/adkinetix/_kinetix_controller.py
ophyd_async/epics/adkinetix/_kinetix_io.py
ophyd_async/epics/adpilatus/__init__.py
ophyd_async/epics/adpilatus/_pilatus.py
ophyd_async/epics/adpilatus/_pilatus_controller.py
ophyd_async-0.14.2.dist-info/licenses/LICENSE
ophyd_async-0.14.2.dist-info/METADATA
ophyd_async-0.14.2.dist-info/WHEEL
ophyd_async-0.14.2.dist-info/top_level.txt
ophyd_async-0.14.2.dist-info/RECORD
