Metadata-Version: 2.4
Name: ophyd-async
Version: 0.14.2
Summary: Asynchronous Bluesky hardware abstraction code, compatible with control systems like EPICS and Tango
Author-email: Tom Cobb <tom.cobb@diamond.ac.uk>
License: BSD 3-Clause License
Project-URL: GitHub, https://github.com/bluesky/ophyd-async
Classifier: Development Status :: 3 - Alpha
Classifier: License :: OSI Approved :: BSD License
Classifier: Programming Language :: Python :: 3.11
Classifier: Programming Language :: Python :: 3.12
Classifier: Programming Language :: Python :: 3.13
Requires-Python: >=3.11
License-File: LICENSE
Requires-Dist: numpy
Requires-Dist: bluesky>=1.13.1rc2
Requires-Dist: event-model>=1.23
Requires-Dist: pyyaml
Requires-Dist: colorlog
Requires-Dist: pydantic>=2.0
Requires-Dist: pydantic-numpy
Requires-Dist: stamina>=23.1.0
Requires-Dist: scanspec>=0.8
Requires-Dist: velocity-profile
Provides-Extra: sim
Requires-Dist: h5py; extra == "sim"
Provides-Extra: ca
Requires-Dist: aioca>=2.0a4; extra == "ca"
Provides-Extra: pva
Requires-Dist: p4p>=4.2.0; extra == "pva"
Provides-Extra: tango
Requires-Dist: pytango>=10.0.2; extra == "tango"
Provides-Extra: demo
Requires-Dist: ipython; extra == "demo"
Requires-Dist: matplotlib; extra == "demo"
Requires-Dist: pyqt6; extra == "demo"
Dynamic: license-file
